[
    {
        "name": "M_R2410",
        "map_asset": "r2410.glb",
        "pos": "-500, 0, 0",
        "rot": "0, 0, 0",
        "scale": "1, 1, 1"
    },
    {
        "name": "O_S00SKY12R",
        "map_asset": "s00sky12r.glb",
        "pos": "0, 0, 0",
        "rot": "0, 0, 0",
        "scale": "13, 13, 13"
    },
    {
        "name": "O_S00SKY09R",
        "map_asset": "s00sky09r.glb",
        "pos": "0, 0, 0",
        "rot": "0, 0, 0",
        "scale": "13, 13, 13"
    },
    {
        "name": "O_S00SKY09R",
        "map_asset": "s00sky09r.glb",
        "pos": "0, 0, 0",
        "rot": "0, -0.5, 0",
        "scale": "13, 13, 13"
    },
    {
        "name": "O_S00SKY05R",
        "map_asset": "s00sky05r.glb",
        "pos": "0, 0, 0",
        "rot": "0, 0, 0",
        "scale": "13, 13, 13"
    },
    {
        "name": "O_S00SKY14R",
        "map_asset": "s00sky14r.glb",
        "pos": "0, 0, 0",
        "rot": "0, 0, 0",
        "scale": "13, 13, 13"
    },
    {
        "name": "O_S00SKY14R",
        "map_asset": "s00sky14r.glb",
        "pos": "0, 0, 0",
        "rot": "0, 0, 0",
        "scale": "13, 13, 13"
    },
    {
        "name": "O_S00SKY02R",
        "map_asset": "s00sky02r.glb",
        "pos": "0, 0, 0",
        "rot": "0, 0, 0",
        "scale": "13, 13, 13"
    },
    {
        "name": "O_S00SKY16R",
        "map_asset": "s00sky16r.glb",
        "pos": "0, 0, 0",
        "rot": "0, 0, 0",
        "scale": "13, 13, 13"
    },
    {
        "name": "O_R20OBJ90",
        "map_asset": "r20obj90.glb",
        "pos": "0, 0, 0",
        "rot": "0, 0, 0",
        "scale": "3, 4, 3"
    },
    {
        "name": "O_R20OBJ90",
        "map_asset": "r20obj90.glb",
        "pos": "0, 0, 0",
        "rot": "0, 2.094395, 0",
        "scale": "3, 3.5, 3"
    },
    {
        "name": "O_R20OBJ90",
        "map_asset": "r20obj90.glb",
        "pos": "0, 0, 0",
        "rot": "0, 4.18879, 0",
        "scale": "3, 4.5, 3"
    },
    {
        "name": "O_D70HOU11",
        "map_asset": "d70hou11.glb",
        "pos": "-296.541, -6.5, 1448.503",
        "rot": "0, 3.752458, 0",
        "scale": "0.75, 0.75, 0.75"
    },
    {
        "name": "O_C00OBJ00",
        "map_asset": "c00obj00.glb",
        "pos": "-884, -7, -371",
        "rot": "0, 0, 0",
        "scale": "0.8, 0.8, 0.8"
    },
    {
        "name": "O_S00TRS00",
        "map_asset": "s00trs00.glb",
        "pos": "137.45, 1, -133.971",
        "rot": "0, 6.011961, 0",
        "scale": "1, 1, 1"
    },
    {
        "name": "O_S00TRS02",
        "map_asset": "s00trs02.glb",
        "pos": "206.831, -1.773, -73.72",
        "rot": "0, 1.092681, 0",
        "scale": "1, 1, 1"
    },
    {
        "name": "O_S00TRS00",
        "map_asset": "s00trs00.glb",
        "pos": "34, 2.5, -115",
        "rot": "0, 5, 0",
        "scale": "1, 1, 1"
    },
    {
        "name": "O_S00TRS09",
        "map_asset": "s00trs09.glb",
        "pos": "44, -6.5, -36.5",
        "rot": "0, 3.1, 0",
        "scale": "1, 1, 1"
    },
    {
        "name": "O_R24OBJ11",
        "map_asset": "r24obj11.glb",
        "pos": "290.991, -2, -73.282",
        "rot": "0, 6.072157, 0",
        "scale": "1, 1, 1"
    },
    {
        "name": "O_S00EVT04",
        "map_asset": "s00evt04.glb",
        "pos": "-25, 0.25, -88",
        "rot": "0, 1.570796, 0",
        "scale": "1, 1, 1"
    },
    {
        "name": "O_S00EVT00",
        "map_asset": "s00evt00.glb",
        "pos": "312, -2, -44",
        "rot": "0, 0.7853982, 0",
        "scale": "1, 1, 1"
    },
    {
        "name": "O_S00EVT00",
        "map_asset": "s00evt00.glb",
        "pos": "296.059, -1.992, -84.018",
        "rot": "0, 0, 0",
        "scale": "1, 1, 1"
    },
    {
        "name": "O_V64CAR00",
        "map_asset": "v64car00.glb",
        "pos": "130.173, 1, -131.176",
        "rot": "0, 1.292504, 0",
        "scale": "1, 1, 1"
    },
    {
        "name": "O_R20OBJ92",
        "map_asset": "r20obj92.glb",
        "pos": "196.079, -11, 202.083",
        "rot": "0, 2.582249, 0",
        "scale": "1.2, 1.2, 1.2"
    },
    {
        "name": "O_R20OBJ92",
        "map_asset": "r20obj92.glb",
        "pos": "119.077, -11, -366.704",
        "rot": "0, 5.624586, 0",
        "scale": "1.2, 1.2, 1.2"
    },
    {
        "name": "O_R30LIG00",
        "map_asset": "r30lig00.glb",
        "pos": "-38.991, 2, -91.219",
        "rot": "0, 0, 0",
        "scale": "1, 1, 1"
    },
    {
        "name": "O_R30LIG00",
        "map_asset": "r30lig00.glb",
        "pos": "-38.407, 1, -70.927",
        "rot": "0, 0, 0",
        "scale": "1, 1, 1"
    },
    {
        "name": "O_R30LIG00",
        "map_asset": "r30lig00.glb",
        "pos": "-52.417, 0.448, -73.57",
        "rot": "0, 0, 0",
        "scale": "1, 1, 1"
    },
    {
        "name": "O_R30LIG00",
        "map_asset": "r30lig00.glb",
        "pos": "-71.879, 0, -55.317",
        "rot": "0, 0, 0",
        "scale": "1, 1, 1"
    },
    {
        "name": "O_R30LIG00",
        "map_asset": "r30lig00.glb",
        "pos": "-3.982, 0, -82.314",
        "rot": "0, 0, 0",
        "scale": "1, 1, 1"
    },
    {
        "name": "O_R30LIG00",
        "map_asset": "r30lig00.glb",
        "pos": "17.364, 0, -94.805",
        "rot": "0, 0, 0",
        "scale": "1, 1, 1"
    },
    {
        "name": "O_R30LIG00",
        "map_asset": "r30lig00.glb",
        "pos": "42.533, 0, -89.251",
        "rot": "0, 0, 0",
        "scale": "1, 1, 1"
    },
    {
        "name": "O_R30LIG00",
        "map_asset": "r30lig00.glb",
        "pos": "90.984, -0.373, -101.903",
        "rot": "0, 0, 0",
        "scale": "1, 1, 1"
    },
    {
        "name": "O_R30LIG00",
        "map_asset": "r30lig00.glb",
        "pos": "117.873, 0.5, -97.295",
        "rot": "0, 0, 0",
        "scale": "1, 1, 1"
    },
    {
        "name": "O_R30LIG00",
        "map_asset": "r30lig00.glb",
        "pos": "142.224, 0.5, -110.895",
        "rot": "0, 0, 0",
        "scale": "1, 1, 1"
    },
    {
        "name": "O_R30LIG00",
        "map_asset": "r30lig00.glb",
        "pos": "163.135, -0.392, -86.606",
        "rot": "0, 0, 0",
        "scale": "1, 1, 1"
    },
    {
        "name": "O_R30LIG00",
        "map_asset": "r30lig00.glb",
        "pos": "196.339, 0.542, -94.722",
        "rot": "0, 0, 0",
        "scale": "1, 1, 1"
    },
    {
        "name": "O_R30LIG00",
        "map_asset": "r30lig00.glb",
        "pos": "229.008, 1.374, -86.42",
        "rot": "0, 0, 0",
        "scale": "1, 1, 1"
    },
    {
        "name": "O_R30LIG00",
        "map_asset": "r30lig00.glb",
        "pos": "261.941, -0.747, -85.881",
        "rot": "0, 0, 0",
        "scale": "1, 1, 1"
    },
    {
        "name": "O_R30LIG00",
        "map_asset": "r30lig00.glb",
        "pos": "282.473, -1.809, -60.867",
        "rot": "0, 0, 0",
        "scale": "1, 1, 1"
    },
    {
        "name": "O_R30LIG00",
        "map_asset": "r30lig00.glb",
        "pos": "301.191, -2, -78.756",
        "rot": "0, 0, 0",
        "scale": "1, 1, 1"
    },
    {
        "name": "O_R30LIG00",
        "map_asset": "r30lig00.glb",
        "pos": "311.16, -2, -55.141",
        "rot": "0, 0, 0",
        "scale": "1, 1, 1"
    },
    {
        "name": "O_R30LIG00",
        "map_asset": "r30lig00.glb",
        "pos": "316.641, -2.5, -31.118",
        "rot": "0, 0, 0",
        "scale": "1, 1, 1"
    },
    {
        "name": "O_R30LIG00",
        "map_asset": "r30lig00.glb",
        "pos": "336.154, -3.5, -34.58",
        "rot": "0, 0, 0",
        "scale": "1, 1, 1"
    },
    {
        "name": "O_R30LIG00",
        "map_asset": "r30lig00.glb",
        "pos": "346.063, -4, -14.9",
        "rot": "0, 0, 0",
        "scale": "1, 1, 1"
    },
    {
        "name": "O_R30LIG00",
        "map_asset": "r30lig00.glb",
        "pos": "374.945, -5, -18.909",
        "rot": "0, 0, 0",
        "scale": "1, 1, 1"
    },
    {
        "name": "O_R00PLT00",
        "map_asset": "r00plt00.glb",
        "pos": "-71.401, 0, -57.694",
        "rot": "0, 0.7994655, 0",
        "scale": "1.1, 1.1, 1.1"
    },
    {
        "name": "O_R00PLT00",
        "map_asset": "r00plt00.glb",
        "pos": "-64.727, 0, -75.255",
        "rot": "0, 0.7994655, 0",
        "scale": "1.1, 1.1, 1.1"
    },
    {
        "name": "O_R00PLT00",
        "map_asset": "r00plt00.glb",
        "pos": "-43.383, 1, -63.155",
        "rot": "0, 0.7994655, 0",
        "scale": "1.1, 1.1, 1.1"
    },
    {
        "name": "O_R00PLT00",
        "map_asset": "r00plt00.glb",
        "pos": "-37.097, 2, -92.686",
        "rot": "0, 0.7994655, 0",
        "scale": "1.1, 1.1, 1.1"
    },
    {
        "name": "O_R00PLT00",
        "map_asset": "r00plt00.glb",
        "pos": "-55.593, 6, -87.421",
        "rot": "0, 0.7994655, 0",
        "scale": "1.1, 1.1, 1.1"
    },
    {
        "name": "O_R00PLT00",
        "map_asset": "r00plt00.glb",
        "pos": "-37.589, 1.447, -79.394",
        "rot": "0, 0.7994655, 0",
        "scale": "1.1, 1.1, 1.1"
    },
    {
        "name": "O_R00PLT00",
        "map_asset": "r00plt00.glb",
        "pos": "-12.467, 0, -93.865",
        "rot": "0, 0.7994655, 0",
        "scale": "1.1, 1.1, 1.1"
    },
    {
        "name": "O_R00PLT00",
        "map_asset": "r00plt00.glb",
        "pos": "7.327, -0.041, -79.673",
        "rot": "0, 0.7994655, 0",
        "scale": "1.1, 1.1, 1.1"
    },
    {
        "name": "O_R00PLT00",
        "map_asset": "r00plt00.glb",
        "pos": "12.958, 0.351, -95.742",
        "rot": "0, 0.7994655, 0",
        "scale": "1.1, 1.1, 1.1"
    },
    {
        "name": "O_R00PLT00",
        "map_asset": "r00plt00.glb",
        "pos": "34.514, 2.5, -117.947",
        "rot": "0, 5.439685, 0",
        "scale": "1.1, 1.1, 1.1"
    },
    {
        "name": "O_R00PLT00",
        "map_asset": "r00plt00.glb",
        "pos": "45.745, -2.124, -111.449",
        "rot": "0, 4.645804, 0",
        "scale": "1.1, 1.1, 1.1"
    },
    {
        "name": "O_R00PLT00",
        "map_asset": "r00plt00.glb",
        "pos": "44.505, 0, -102.281",
        "rot": "0, 3.681982, 0",
        "scale": "1.1, 1.1, 1.1"
    },
    {
        "name": "O_R00PLT00",
        "map_asset": "r00plt00.glb",
        "pos": "43.286, -2.446, -74.576",
        "rot": "0, 4.645804, 0",
        "scale": "1.1, 1.1, 1.1"
    },
    {
        "name": "O_R00PLT00",
        "map_asset": "r00plt00.glb",
        "pos": "32.513, -2.815, -69.901",
        "rot": "0, 4.645804, 0",
        "scale": "1.1, 1.1, 1.1"
    },
    {
        "name": "O_R00PLT00",
        "map_asset": "r00plt00.glb",
        "pos": "25.852, 0, -79.734",
        "rot": "0, 5.599766, 0",
        "scale": "1.1, 1.1, 1.1"
    },
    {
        "name": "O_R00PLT00",
        "map_asset": "r00plt00.glb",
        "pos": "31.69, -4.06, -46.88",
        "rot": "0, 5.599766, 0",
        "scale": "1.1, 1.1, 1.1"
    },
    {
        "name": "O_R00PLT00",
        "map_asset": "r00plt00.glb",
        "pos": "46.294, -5, -60.781",
        "rot": "0, 5.599766, 0",
        "scale": "1.1, 1.1, 1.1"
    },
    {
        "name": "O_R00PLT00",
        "map_asset": "r00plt00.glb",
        "pos": "47.414, -6.5, -35.847",
        "rot": "0, 5.599766, 0",
        "scale": "1.1, 1.1, 1.1"
    },
    {
        "name": "O_R00PLT00",
        "map_asset": "r00plt00.glb",
        "pos": "39.673, -6.5, -37.612",
        "rot": "0, 0.5989795, 0",
        "scale": "1.1, 1.1, 1.1"
    },
    {
        "name": "O_R00PLT00",
        "map_asset": "r00plt00.glb",
        "pos": "26.344, -0.001, -16.018",
        "rot": "0, 0.5989795, 0",
        "scale": "1.1, 1.1, 1.1"
    },
    {
        "name": "O_R00PLT00",
        "map_asset": "r00plt00.glb",
        "pos": "41.138, -0.137, -26.118",
        "rot": "0, 0.5989795, 0",
        "scale": "1.1, 1.1, 1.1"
    },
    {
        "name": "O_R00PLT00",
        "map_asset": "r00plt00.glb",
        "pos": "38.451, 0.534, -12.497",
        "rot": "0, 0.5989795, 0",
        "scale": "1.1, 1.1, 1.1"
    },
    {
        "name": "O_R00PLT00",
        "map_asset": "r00plt00.glb",
        "pos": "18.252, -2.76, -49.923",
        "rot": "0, 0.5989795, 0",
        "scale": "1.1, 1.1, 1.1"
    },
    {
        "name": "O_R00PLT00",
        "map_asset": "r00plt00.glb",
        "pos": "8.376, 1, -108.39",
        "rot": "0, 0.7994655, 0",
        "scale": "1.1, 1.1, 1.1"
    },
    {
        "name": "O_R00PLT00",
        "map_asset": "r00plt00.glb",
        "pos": "38.019, 0, -83.096",
        "rot": "0, 4.406852, 0",
        "scale": "1.1, 1.1, 1.1"
    },
    {
        "name": "O_R00PLT00",
        "map_asset": "r00plt00.glb",
        "pos": "1.062, 2.204, -73.549",
        "rot": "0, 4.406852, 0",
        "scale": "1.1, 1.1, 1.1"
    },
    {
        "name": "O_R00PLT00",
        "map_asset": "r00plt00.glb",
        "pos": "-19.113, 3.879, -76.472",
        "rot": "0, 4.406852, 0",
        "scale": "1.1, 1.1, 1.1"
    },
    {
        "name": "O_R00PLT00",
        "map_asset": "r00plt00.glb",
        "pos": "-23.308, 5.868, -63.174",
        "rot": "0, 4.406852, 0",
        "scale": "1.1, 1.1, 1.1"
    },
    {
        "name": "O_R00PLT00",
        "map_asset": "r00plt00.glb",
        "pos": "84.586, 0, -90.6",
        "rot": "0, 3.681982, 0",
        "scale": "1.1, 1.1, 1.1"
    },
    {
        "name": "O_R00PLT00",
        "map_asset": "r00plt00.glb",
        "pos": "97.586, -1.054, -76.597",
        "rot": "0, 3.681982, 0",
        "scale": "1.1, 1.1, 1.1"
    },
    {
        "name": "O_R00PLT00",
        "map_asset": "r00plt00.glb",
        "pos": "86.318, -8, -66.522",
        "rot": "0, 5.330724, 0",
        "scale": "1.1, 1.1, 1.1"
    },
    {
        "name": "O_R00PLT00",
        "map_asset": "r00plt00.glb",
        "pos": "85.321, -6, -29.494",
        "rot": "0, 5.330724, 0",
        "scale": "1.1, 1.1, 1.1"
    },
    {
        "name": "O_R00PLT00",
        "map_asset": "r00plt00.glb",
        "pos": "107.124, -1.839, -45.599",
        "rot": "0, 5.330724, 0",
        "scale": "1.1, 1.1, 1.1"
    },
    {
        "name": "O_R00PLT00",
        "map_asset": "r00plt00.glb",
        "pos": "114.31, 1.348, -35.498",
        "rot": "0, 5.330724, 0",
        "scale": "1.1, 1.1, 1.1"
    },
    {
        "name": "O_R00PLT00",
        "map_asset": "r00plt00.glb",
        "pos": "110.734, 1.348, -56.696",
        "rot": "0, 5.330724, 0",
        "scale": "1.1, 1.1, 1.1"
    },
    {
        "name": "O_R00PLT00",
        "map_asset": "r00plt00.glb",
        "pos": "106.315, 0.622, -60.956",
        "rot": "0, 5.330724, 0",
        "scale": "1.1, 1.1, 1.1"
    },
    {
        "name": "O_R00PLT00",
        "map_asset": "r00plt00.glb",
        "pos": "110.108, 2.064, -79.017",
        "rot": "0, 5.330724, 0",
        "scale": "1.1, 1.1, 1.1"
    },
    {
        "name": "O_R00PLT00",
        "map_asset": "r00plt00.glb",
        "pos": "83.794, 0, -102.184",
        "rot": "0, 2.716029, 0",
        "scale": "1.1, 1.1, 1.1"
    },
    {
        "name": "O_R00PLT00",
        "map_asset": "r00plt00.glb",
        "pos": "90.977, 1.979, -114.131",
        "rot": "0, 4.69792, 0",
        "scale": "1.1, 1.1, 1.1"
    },
    {
        "name": "O_R00PLT00",
        "map_asset": "r00plt00.glb",
        "pos": "107.303, 0, -91.193",
        "rot": "0, 4.69792, 0",
        "scale": "1.1, 1.1, 1.1"
    },
    {
        "name": "O_R00PLT00",
        "map_asset": "r00plt00.glb",
        "pos": "111.63, 0.017, -110.493",
        "rot": "0, 2.564203, 0",
        "scale": "1.1, 1.1, 1.1"
    },
    {
        "name": "O_R00PLT00",
        "map_asset": "r00plt00.glb",
        "pos": "102.19, -1.797, -109.278",
        "rot": "0, 0.8206364, 0",
        "scale": "1.1, 1.1, 1.1"
    },
    {
        "name": "O_R00PLT00",
        "map_asset": "r00plt00.glb",
        "pos": "110.31, -1.943, -127.74",
        "rot": "0, 2.564203, 0",
        "scale": "1.1, 1.1, 1.1"
    },
    {
        "name": "O_R00PLT00",
        "map_asset": "r00plt00.glb",
        "pos": "141.986, 1, -131.087",
        "rot": "0, 2.564203, 0",
        "scale": "1.1, 1.1, 1.1"
    },
    {
        "name": "O_R00PLT00",
        "map_asset": "r00plt00.glb",
        "pos": "145.263, 0.307, -115.285",
        "rot": "0, 4.947066, 0",
        "scale": "1.1, 1.1, 1.1"
    },
    {
        "name": "O_R00PLT00",
        "map_asset": "r00plt00.glb",
        "pos": "154.989, 4.169, -126.56",
        "rot": "0, 4.947066, 0",
        "scale": "1.1, 1.1, 1.1"
    },
    {
        "name": "O_R00PLT00",
        "map_asset": "r00plt00.glb",
        "pos": "140.045, 0.5, -92.686",
        "rot": "0, 4.947066, 0",
        "scale": "1.1, 1.1, 1.1"
    },
    {
        "name": "O_R00PLT00",
        "map_asset": "r00plt00.glb",
        "pos": "154.825, 0, -92.507",
        "rot": "0, 3.52389, 0",
        "scale": "1.1, 1.1, 1.1"
    },
    {
        "name": "O_R00PLT00",
        "map_asset": "r00plt00.glb",
        "pos": "169.197, -0.5, -105.191",
        "rot": "0, 3.52389, 0",
        "scale": "1.1, 1.1, 1.1"
    },
    {
        "name": "O_R00PLT00",
        "map_asset": "r00plt00.glb",
        "pos": "170.664, -0.5, -96.588",
        "rot": "0, 5.738101, 0",
        "scale": "1.1, 1.1, 1.1"
    },
    {
        "name": "O_R00PLT00",
        "map_asset": "r00plt00.glb",
        "pos": "163.932, -3.051, -70.656",
        "rot": "0, 5.738101, 0",
        "scale": "1.1, 1.1, 1.1"
    },
    {
        "name": "O_R00PLT00",
        "map_asset": "r00plt00.glb",
        "pos": "182.502, -3.051, -61.764",
        "rot": "0, 5.738101, 0",
        "scale": "1.1, 1.1, 1.1"
    },
    {
        "name": "O_R00PLT00",
        "map_asset": "r00plt00.glb",
        "pos": "182.838, -1.975, -53.515",
        "rot": "0, 5.738101, 0",
        "scale": "1.1, 1.1, 1.1"
    },
    {
        "name": "O_R00PLT00",
        "map_asset": "r00plt00.glb",
        "pos": "164.664, 0.097, -48.946",
        "rot": "0, 4.014781, 0",
        "scale": "1.1, 1.1, 1.1"
    },
    {
        "name": "O_R00PLT00",
        "map_asset": "r00plt00.glb",
        "pos": "171.948, 1.773, -40.771",
        "rot": "0, 4.014781, 0",
        "scale": "1.1, 1.1, 1.1"
    },
    {
        "name": "O_R00PLT00",
        "map_asset": "r00plt00.glb",
        "pos": "197.316, -0.495, -76.533",
        "rot": "0, 4.014781, 0",
        "scale": "1.1, 1.1, 1.1"
    },
    {
        "name": "O_R00PLT00",
        "map_asset": "r00plt00.glb",
        "pos": "205.665, -1.614, -74.435",
        "rot": "0, 4.014781, 0",
        "scale": "1.1, 1.1, 1.1"
    },
    {
        "name": "O_R00PLT00",
        "map_asset": "r00plt00.glb",
        "pos": "201.194, -1.149, -67.222",
        "rot": "0, 4.014781, 0",
        "scale": "1.1, 1.1, 1.1"
    },
    {
        "name": "O_R00PLT00",
        "map_asset": "r00plt00.glb",
        "pos": "232.842, -0.628, -60.891",
        "rot": "0, 4.014781, 0",
        "scale": "1.1, 1.1, 1.1"
    },
    {
        "name": "O_R00PLT00",
        "map_asset": "r00plt00.glb",
        "pos": "240.221, 0, -76.147",
        "rot": "0, 4.014781, 0",
        "scale": "1.1, 1.1, 1.1"
    },
    {
        "name": "O_R00PLT00",
        "map_asset": "r00plt00.glb",
        "pos": "249.215, -0.062, -76.601",
        "rot": "0, 3.099809, 0",
        "scale": "1.1, 1.1, 1.1"
    },
    {
        "name": "O_R00PLT00",
        "map_asset": "r00plt00.glb",
        "pos": "254.105, 0, -92.853",
        "rot": "0, 3.099809, 0",
        "scale": "1.1, 1.1, 1.1"
    },
    {
        "name": "O_R00PLT00",
        "map_asset": "r00plt00.glb",
        "pos": "241.596, 0.018, -101.168",
        "rot": "0, 3.099809, 0",
        "scale": "1.1, 1.1, 1.1"
    },
    {
        "name": "O_R00PLT00",
        "map_asset": "r00plt00.glb",
        "pos": "229.628, 1.297, -98.981",
        "rot": "0, 1.566573, 0",
        "scale": "1.1, 1.1, 1.1"
    },
    {
        "name": "O_R00PLT00",
        "map_asset": "r00plt00.glb",
        "pos": "201.763, 1.22, -97.249",
        "rot": "0, 1.566573, 0",
        "scale": "1.1, 1.1, 1.1"
    },
    {
        "name": "O_R00PLT00",
        "map_asset": "r00plt00.glb",
        "pos": "208.295, 1.915, -85.009",
        "rot": "0, 0.2472433, 0",
        "scale": "1.1, 1.1, 1.1"
    },
    {
        "name": "O_R00PLT00",
        "map_asset": "r00plt00.glb",
        "pos": "160.494, -0.07, -82.496",
        "rot": "0, 4.231237, 0",
        "scale": "1.1, 1.1, 1.1"
    },
    {
        "name": "O_R00PLT00",
        "map_asset": "r00plt00.glb",
        "pos": "225.408, -3.958, -47.443",
        "rot": "0, 3.217968, 0",
        "scale": "1.1, 1.1, 1.1"
    },
    {
        "name": "O_R00PLT00",
        "map_asset": "r00plt00.glb",
        "pos": "219.693, -2.351, -33.788",
        "rot": "0, 3.217968, 0",
        "scale": "1.1, 1.1, 1.1"
    },
    {
        "name": "O_R00PLT00",
        "map_asset": "r00plt00.glb",
        "pos": "237.753, -3.524, -33.737",
        "rot": "0, 1.877974, 0",
        "scale": "1.1, 1.1, 1.1"
    },
    {
        "name": "O_R00PLT00",
        "map_asset": "r00plt00.glb",
        "pos": "246.655, -2.426, -42.528",
        "rot": "0, 1.877974, 0",
        "scale": "1.1, 1.1, 1.1"
    },
    {
        "name": "O_R00PLT00",
        "map_asset": "r00plt00.glb",
        "pos": "254.843, 1.4, -31.435",
        "rot": "0, 1.877974, 0",
        "scale": "1.1, 1.1, 1.1"
    },
    {
        "name": "O_R00PLT00",
        "map_asset": "r00plt00.glb",
        "pos": "276.692, 1.999, -38.979",
        "rot": "0, 1.877974, 0",
        "scale": "1.1, 1.1, 1.1"
    },
    {
        "name": "O_R00PLT00",
        "map_asset": "r00plt00.glb",
        "pos": "272.248, 1.999, -45.468",
        "rot": "0, 1.877974, 0",
        "scale": "1.1, 1.1, 1.1"
    },
    {
        "name": "O_R00PLT00",
        "map_asset": "r00plt00.glb",
        "pos": "264.682, 3.821, -35.665",
        "rot": "0, 1.877974, 0",
        "scale": "1.1, 1.1, 1.1"
    },
    {
        "name": "O_R00PLT00",
        "map_asset": "r00plt00.glb",
        "pos": "255.239, 1.825, -48.732",
        "rot": "0, 1.877974, 0",
        "scale": "1.1, 1.1, 1.1"
    },
    {
        "name": "O_R00PLT00",
        "map_asset": "r00plt00.glb",
        "pos": "246.27, 0, -57.374",
        "rot": "0, 1.877974, 0",
        "scale": "1.1, 1.1, 1.1"
    },
    {
        "name": "O_R00PLT00",
        "map_asset": "r00plt00.glb",
        "pos": "275.554, -1.444, -59.868",
        "rot": "0, 1.877974, 0",
        "scale": "1.1, 1.1, 1.1"
    },
    {
        "name": "O_R00PLT00",
        "map_asset": "r00plt00.glb",
        "pos": "287.192, -2, -51.28",
        "rot": "0, 1.877974, 0",
        "scale": "1.1, 1.1, 1.1"
    },
    {
        "name": "O_R00PLT00",
        "map_asset": "r00plt00.glb",
        "pos": "292.793, -2, -58.865",
        "rot": "0, 0.2783102, 0",
        "scale": "1.1, 1.1, 1.1"
    },
    {
        "name": "O_R00PLT00",
        "map_asset": "r00plt00.glb",
        "pos": "287.92, -2, -75.917",
        "rot": "0, 5.129331, 0",
        "scale": "1.1, 1.1, 1.1"
    },
    {
        "name": "O_R00PLT00",
        "map_asset": "r00plt00.glb",
        "pos": "301.446, -2, -88.563",
        "rot": "0, 5.129331, 0",
        "scale": "1.1, 1.1, 1.1"
    },
    {
        "name": "O_R00PLT00",
        "map_asset": "r00plt00.glb",
        "pos": "310.889, 2.185, -88.09",
        "rot": "0, 5.968939, 0",
        "scale": "1.1, 1.1, 1.1"
    },
    {
        "name": "O_R00PLT00",
        "map_asset": "r00plt00.glb",
        "pos": "309.368, 4.126, -101.81",
        "rot": "0, 3.486016, 0",
        "scale": "1.1, 1.1, 1.1"
    },
    {
        "name": "O_R00PLT00",
        "map_asset": "r00plt00.glb",
        "pos": "337.919, 1.314, -65.285",
        "rot": "0, 5.968939, 0",
        "scale": "1.1, 1.1, 1.1"
    },
    {
        "name": "O_R00PLT00",
        "map_asset": "r00plt00.glb",
        "pos": "343.305, 3.498, -55.611",
        "rot": "0, 5.968939, 0",
        "scale": "1.1, 1.1, 1.1"
    },
    {
        "name": "O_R00PLT00",
        "map_asset": "r00plt00.glb",
        "pos": "335.97, 3.498, -50.248",
        "rot": "0, 4.537472, 0",
        "scale": "1.1, 1.1, 1.1"
    },
    {
        "name": "O_R00PLT00",
        "map_asset": "r00plt00.glb",
        "pos": "333.788, -3.349, -37.896",
        "rot": "0, 4.537472, 0",
        "scale": "1.1, 1.1, 1.1"
    },
    {
        "name": "O_R00PLT00",
        "map_asset": "r00plt00.glb",
        "pos": "313.956, -3.147, -30.667",
        "rot": "0, 4.537472, 0",
        "scale": "1.1, 1.1, 1.1"
    },
    {
        "name": "O_R00PLT00",
        "map_asset": "r00plt00.glb",
        "pos": "303.614, -2, -43.828",
        "rot": "0, 2.825967, 0",
        "scale": "1.1, 1.1, 1.1"
    },
    {
        "name": "O_R00PLT00",
        "map_asset": "r00plt00.glb",
        "pos": "294.003, 1.898, -29.725",
        "rot": "0, 4.537472, 0",
        "scale": "1.1, 1.1, 1.1"
    },
    {
        "name": "O_R00PLT00",
        "map_asset": "r00plt00.glb",
        "pos": "293.755, 3.792, -19.352",
        "rot": "0, 3.003066, 0",
        "scale": "1.1, 1.1, 1.1"
    },
    {
        "name": "O_R00PLT00",
        "map_asset": "r00plt00.glb",
        "pos": "302.442, 3.936, -18.14",
        "rot": "0, 3.003066, 0",
        "scale": "1.1, 1.1, 1.1"
    },
    {
        "name": "O_R00PLT00",
        "map_asset": "r00plt00.glb",
        "pos": "318.932, 1.093, -10.461",
        "rot": "0, 3.003066, 0",
        "scale": "1.1, 1.1, 1.1"
    },
    {
        "name": "O_R00PLT00",
        "map_asset": "r00plt00.glb",
        "pos": "267.967, 4.078, -17.566",
        "rot": "0, 3.003066, 0",
        "scale": "1.1, 1.1, 1.1"
    },
    {
        "name": "O_R00PLT00",
        "map_asset": "r00plt00.glb",
        "pos": "279.486, 2.029, -83.522",
        "rot": "0, 3.003066, 0",
        "scale": "1.1, 1.1, 1.1"
    },
    {
        "name": "O_R00PLT00",
        "map_asset": "r00plt00.glb",
        "pos": "277.346, 4.18, -92.038",
        "rot": "0, 1.964543, 0",
        "scale": "1.1, 1.1, 1.1"
    },
    {
        "name": "O_R00PLT00",
        "map_asset": "r00plt00.glb",
        "pos": "270.638, 4.18, -95.905",
        "rot": "0, 1.964543, 0",
        "scale": "1.1, 1.1, 1.1"
    },
    {
        "name": "O_R00PLT00",
        "map_asset": "r00plt00.glb",
        "pos": "262.425, 3.894, -111.098",
        "rot": "0, 1.964543, 0",
        "scale": "1.1, 1.1, 1.1"
    },
    {
        "name": "O_R00PLT00",
        "map_asset": "r00plt00.glb",
        "pos": "268.687, 0.076, -116.803",
        "rot": "0, 1.964543, 0",
        "scale": "1.1, 1.1, 1.1"
    },
    {
        "name": "O_R00PLT00",
        "map_asset": "r00plt00.glb",
        "pos": "298.849, 2.232, -112.011",
        "rot": "0, 3.907495, 0",
        "scale": "1.1, 1.1, 1.1"
    },
    {
        "name": "O_R00PLT00",
        "map_asset": "r00plt00.glb",
        "pos": "296.031, -1.307, -98.944",
        "rot": "0, 3.907495, 0",
        "scale": "1.1, 1.1, 1.1"
    },
    {
        "name": "O_R00PLT00",
        "map_asset": "r00plt00.glb",
        "pos": "288.901, -1.307, -92.087",
        "rot": "0, 3.907495, 0",
        "scale": "1.1, 1.1, 1.1"
    },
    {
        "name": "O_R00PLT00",
        "map_asset": "r00plt00.glb",
        "pos": "290.111, -1.94, -115.209",
        "rot": "0, 3.907495, 0",
        "scale": "1.1, 1.1, 1.1"
    },
    {
        "name": "O_R00PLT00",
        "map_asset": "r00plt00.glb",
        "pos": "277.97, -2.451, -116.301",
        "rot": "0, 3.907495, 0",
        "scale": "1.1, 1.1, 1.1"
    },
    {
        "name": "O_R00PLT00",
        "map_asset": "r00plt00.glb",
        "pos": "328.552, -2, -71.674",
        "rot": "0, 4.537472, 0",
        "scale": "1.1, 1.1, 1.1"
    },
    {
        "name": "O_R30LIG00",
        "map_asset": "r30lig00.glb",
        "pos": "287.267, -1.172, -94.607",
        "rot": "0, 0, 0",
        "scale": "1, 1, 1"
    },
    {
        "name": "O_R30LIG00",
        "map_asset": "r30lig00.glb",
        "pos": "290.769, -1.622, -107.674",
        "rot": "0, 0, 0",
        "scale": "1, 1, 1"
    },
    {
        "name": "O_R30LIG00",
        "map_asset": "r30lig00.glb",
        "pos": "275.888, -2.894, -118.807",
        "rot": "0, 0, 0",
        "scale": "1, 1, 1"
    },
    {
        "name": "O_R30LIG00",
        "map_asset": "r30lig00.glb",
        "pos": "282.562, -4.332, -130.751",
        "rot": "0, 0, 0",
        "scale": "1, 1, 1"
    },
    {
        "name": "O_R42OBJ12",
        "map_asset": "r42obj12.glb",
        "pos": "315.986, -2, -79.523",
        "rot": "0, 3.264673, 0",
        "scale": "1, 1, 1"
    },
    {
        "name": "O_C00OBJ01",
        "map_asset": "c00obj01.glb",
        "pos": "319.795, -2, -79.479",
        "rot": "0, 4.835434, 0",
        "scale": "1, 1, 1"
    },
    {
        "name": "O_C06ISU00",
        "map_asset": "c06isu00.glb",
        "pos": "318.202, -2, -79.426",
        "rot": "0, 0.1230457, 0",
        "scale": "1, 1, 1"
    },
    {
        "name": "O_C06ISU00",
        "map_asset": "c06isu00.glb",
        "pos": "316.054, -2, -79.152",
        "rot": "0, 0.1230457, 0",
        "scale": "1, 1, 1"
    },
    {
        "name": "O_C06ISU00",
        "map_asset": "c06isu00.glb",
        "pos": "313.889, -2, -78.889",
        "rot": "0, 0.1230457, 0",
        "scale": "1, 1, 1"
    },
    {
        "name": "O_S00BRK10",
        "map_asset": "s00brk10.glb",
        "pos": "197.084, -0.192, -77.965",
        "rot": "0, 1.328929, 0",
        "scale": "1, 1, 1"
    },
    {
        "name": "O_S00BRK10",
        "map_asset": "s00brk10.glb",
        "pos": "98.331, -0.935, -77.942",
        "rot": "0, 4.420151, 0",
        "scale": "1, 1, 1"
    },
    {
        "name": "O_S00BRK10",
        "map_asset": "s00brk10.glb",
        "pos": "87.08, -6, -29.181",
        "rot": "0, 3.352079, 0",
        "scale": "1, 1, 1"
    },
    {
        "name": "O_S00BRK10",
        "map_asset": "s00brk10.glb",
        "pos": "10.8, -0.375, -74.835",
        "rot": "0, 5.097199, 0",
        "scale": "1, 1, 1"
    },
    {
        "name": "O_S00BRK10",
        "map_asset": "s00brk10.glb",
        "pos": "86.642, 0.12, -90.149",
        "rot": "0, 2.217319, 0",
        "scale": "1, 1, 1"
    },
    {
        "name": "O_S00BRK10",
        "map_asset": "s00brk10.glb",
        "pos": "143.794, 0.5, -89.625",
        "rot": "0, 4.413938, 0",
        "scale": "1, 1, 1"
    },
    {
        "name": "O_S00BRK20",
        "map_asset": "s00brk20.glb",
        "pos": "127.945, 0.989, -135.747",
        "rot": "0, 2.87927, 0",
        "scale": "1, 1, 1"
    },
    {
        "name": "O_S00BRK20",
        "map_asset": "s00brk20.glb",
        "pos": "213.911, 1.992, -103.314",
        "rot": "0, 1.530252, 0",
        "scale": "1, 1, 1"
    },
    {
        "name": "O_S00BRK20",
        "map_asset": "s00brk20.glb",
        "pos": "310.505, -1.988, -78.605",
        "rot": "0, 0.7324623, 0",
        "scale": "1, 1, 1"
    },
    {
        "name": "O_S00BRK20",
        "map_asset": "s00brk20.glb",
        "pos": "171.097, -0.49, -103.631",
        "rot": "0, 0.8681617, 0",
        "scale": "1, 1, 1"
    },
    {
        "name": "O_S00BRK20",
        "map_asset": "s00brk20.glb",
        "pos": "311.431, -2, -78.588",
        "rot": "0, 6.172392, 0",
        "scale": "1, 1, 1"
    },
    {
        "name": "O_S00BRK20",
        "map_asset": "s00brk20.glb",
        "pos": "5.491, 0.776, -106.411",
        "rot": "0, 1.871307, 0",
        "scale": "1, 1, 1"
    },
    {
        "name": "O_S00BRK20",
        "map_asset": "s00brk20.glb",
        "pos": "46.295, -4.99, -59.456",
        "rot": "0, 4.55393, 0",
        "scale": "1, 1, 1"
    },
    {
        "name": "O_S00BRK33",
        "map_asset": "s00brk33.glb",
        "pos": "27.851, -3.51, -27.766",
        "rot": "0, 4.885962, 0",
        "scale": "1, 1, 1"
    },
    {
        "name": "O_S00BRK33",
        "map_asset": "s00brk33.glb",
        "pos": "330.284, -2.028, -77.027",
        "rot": "0, 0.5104216, 0",
        "scale": "1, 1, 1"
    },
    {
        "name": "O_S00BRK33",
        "map_asset": "s00brk33.glb",
        "pos": "330.838, -2.011, -76.087",
        "rot": "0, 0.5053251, 0",
        "scale": "1, 1, 1"
    },
    {
        "name": "O_S00BRK33",
        "map_asset": "s00brk33.glb",
        "pos": "243.057, -0.008, -100.713",
        "rot": "0, 6.115912, 0",
        "scale": "1, 1, 1"
    },
    {
        "name": "O_S00BRK33",
        "map_asset": "s00brk33.glb",
        "pos": "126.764, 0.978, -135.797",
        "rot": "0, 0.08686504, 0",
        "scale": "1, 1, 1"
    },
    {
        "name": "O_S00BRK33",
        "map_asset": "s00brk33.glb",
        "pos": "87.791, -8.008, -62.621",
        "rot": "0, 4.786478, 0",
        "scale": "1, 1, 1"
    },
    {
        "name": "O_S00BRK33",
        "map_asset": "s00brk33.glb",
        "pos": "87.732, -8.021, -63.71",
        "rot": "0, 4.753928, 0",
        "scale": "1, 1, 1"
    },
    {
        "name": "O_S00BRK33",
        "map_asset": "s00brk33.glb",
        "pos": "29.029, -3.518, -28.214",
        "rot": "0, 5.118719, 0",
        "scale": "1, 1, 1"
    },
    {
        "name": "O_S00BRK33",
        "map_asset": "s00brk33.glb",
        "pos": "247.764, -0.011, -56.78",
        "rot": "0, 1.046185, 0",
        "scale": "1, 1, 1"
    },
    {
        "name": "O_S00BRK33",
        "map_asset": "s00brk33.glb",
        "pos": "40.165, -0.012, -103.09",
        "rot": "0, 1.71613, 0",
        "scale": "1, 1, 1"
    },
    {
        "name": "O_V20AIR00",
        "map_asset": "v20air00.glb",
        "pos": "-773.42, 274.444, -301.691",
        "rot": "0, 4.139013, 0",
        "scale": "1, 1, 1"
    }
]